config_server.cpython-310-x86_64-linux-gnu.so
config_server.pyi
config_server/__init__.pyi
config_server/cli.pyi
config_server/decorators.pyi
config_server/leaf.pyi
config_server/node.pyi
config_server/utils.pyi
config_server/static/index.html
config_server.build/.gitignore
config_server-0.6.5.dist-info/METADATA
config_server-0.6.5.dist-info/WHEEL
config_server-0.6.5.dist-info/top_level.txt
config_server-0.6.5.dist-info/RECORD
