Metadata-Version: 2.1
Name: config-server
Version: 0.6.5
Summary: To build a extendable config server.
Author: laorange
Author-email: laorange6666@gmail.com
Requires-Python: >=3.8, <3.12
Requires-Dist: loguru
Requires-Dist: rich
Requires-Dist: noneprompt
Requires-Dist: pyyaml>=6
Requires-Dist: pydantic>=2
Requires-Dist: fastapi>=0.100.0
Requires-Dist: polyfactory
Requires-Dist: uvicorn
